tests/__init__.py
tests/test.py
vcf2cytosure/__init__.py
vcf2cytosure/__version__.py
vcf2cytosure/vcf2cytosure.py
vcf2cytosure/constants/__init__.py
vcf2cytosure-0.9.1.dist-info/LICENSE
vcf2cytosure-0.9.1.dist-info/METADATA
vcf2cytosure-0.9.1.dist-info/WHEEL
vcf2cytosure-0.9.1.dist-info/entry_points.txt
vcf2cytosure-0.9.1.dist-info/top_level.txt
vcf2cytosure-0.9.1.dist-info/RECORD
