Metadata-Version: 2.1
Name: vcf2cytosure
Version: 0.9.1
Summary: Convert VCF with structural variations to CytoSure format
Home-page: https://github.com/NBISweden/vcf2cytosure
Author: Marcel Martin
Author-email: marcel.martin@scilifelab.se
Maintainer: Daniel Nilsson
Maintainer-email: daniel.nilsson@scilifelab.se
License: MIT
Platform: UNKNOWN
Classifier: Development Status :: 3 - Alpha
Classifier: Environment :: Console
Classifier: Intended Audience :: Science/Research
Classifier: License :: OSI Approved :: MIT License
Classifier: Natural Language :: English
Classifier: Programming Language :: Python :: 3
Classifier: Topic :: Scientific/Engineering :: Bio-Informatics
Requires-Dist: lxml
Requires-Dist: pandas
Requires-Dist: cyvcf2
